multiproof/__init__.py
multiproof/bytes.py
multiproof/core.py
multiproof/py.typed
multiproof/standard.py
multiproof/tests/__init__.py
multiproof/tests/test_standard.py
multiproof/utils.py
multiproof-0.1.10.dist-info/LICENSE
multiproof-0.1.10.dist-info/METADATA
multiproof-0.1.10.dist-info/WHEEL
multiproof-0.1.10.dist-info/RECORD
