Metadata-Version: 2.1
Name: multiproof
Version: 0.1.10
Summary: A Python library to generate merkle trees and merkle proofs.
Home-page: https://github.com/stakewise/multiproof
License: MIT
Keywords: merkle-tree,multiproof
Author: StakeWise Labs
Author-email: info@stakewise.io
Requires-Python: >=3.10,<4.0
Classifier: License :: OSI Approved :: MIT License
Classifier: Programming Language :: Python :: 3
Classifier: Programming Language :: Python :: 3.10
Classifier: Programming Language :: Python :: 3.11
Classifier: Programming Language :: Python :: 3.12
Classifier: Programming Language :: Python :: 3.13
Requires-Dist: eth-abi (>=5.0.1,<6.0.0)
Requires-Dist: eth-hash[pycryptodome] (>=0.7.0,<0.8.0)
Requires-Dist: eth-utils (>=5.1.0)
Project-URL: Repository, https://github.com/stakewise/multiproof
